point_annotator-2.0.0-py3.7-nspkg.pth
pointannotator/annotate_samples.py
pointannotator/plotting.py
pointannotator/utils.py
pointannotator/examples/dendrtic_cells_annotation.ipynb
pointannotator/examples/human_pancreas_annotation.ipynb
pointannotator/examples/mouse_pancreas_annotation.ipynb
pointannotator/tests/__init__.py
pointannotator/tests/test_annotate_samples.py
point_annotator-2.0.0.dist-info/LICENSE
point_annotator-2.0.0.dist-info/METADATA
point_annotator-2.0.0.dist-info/WHEEL
point_annotator-2.0.0.dist-info/namespace_packages.txt
point_annotator-2.0.0.dist-info/top_level.txt
point_annotator-2.0.0.dist-info/RECORD
